cxextractor
