Metadata-Version: 2.1
Name: cxextractor
Version: 0.0.4
Summary: cxextractor
Home-page: https://github.com/chrislinan/cx-extractor-python
Author: linan
Author-email: chrisbarry@sina.com
License: UNKNOWN
Platform: UNKNOWN
Classifier: Programming Language :: Python :: 3
Classifier: License :: OSI Approved :: MIT License
Classifier: Operating System :: OS Independent
